llm_log_analyzer/__init__.py
llm_log_analyzer/analyze_log.py
llm_log_analyzer/constants.py
llm_log_analyzer/environment.py
llm_log_analyzer/llm_client.py
llm_log_analyzer/presets.py
llm_log_analyzer/utils.py
llm_log_analyzer/patterns/android.txt
llm_log_analyzer/patterns/flutter.txt
llm_log_analyzer/patterns/generic.txt
llm_log_analyzer/patterns/ios.txt
llm_log_analyzer/patterns/unity.txt
llm_log_analyzer/prompts/android.txt
llm_log_analyzer/prompts/flutter.txt
llm_log_analyzer/prompts/generic.txt
llm_log_analyzer/prompts/ios.txt
llm_log_analyzer/prompts/unity.txt
llm_log_analyzer/providers/__init__.py
llm_log_analyzer/providers/base.py
llm_log_analyzer/providers/bedrock.py
llm_log_analyzer/providers/claude.py
llm_log_analyzer/providers/factory.py
llm_log_analyzer/providers/gemini.py
llm_log_analyzer/providers/openai.py
llm_log_analyzer/providers/types.py
llm_log_analyzer-1.2.1.dist-info/licenses/LICENSE
llm_log_analyzer-1.2.1.dist-info/METADATA
llm_log_analyzer-1.2.1.dist-info/WHEEL
llm_log_analyzer-1.2.1.dist-info/entry_points.txt
llm_log_analyzer-1.2.1.dist-info/top_level.txt
llm_log_analyzer-1.2.1.dist-info/RECORD
