Metadata-Version: 2.4
Name: llm-log-analyzer
Version: 1.2.1
Summary: AI-powered log analyzer for CI environments using LLMs
Author-email: Renato Freitas <renatoaf.dev@gmail.com>
Maintainer-email: Renato Freitas <renatoaf.dev@gmail.com>
License-Expression: MIT
Project-URL: Homepage, https://github.com/renatoaf/llm-log-analyzer
Project-URL: Repository, https://github.com/renatoaf/llm-log-analyzer
Project-URL: Issues, https://github.com/renatoaf/llm-log-analyzer/issues
Project-URL: Documentation, https://github.com/renatoaf/llm-log-analyzer#readme
Keywords: unity,build,log,analyzer,ci,automation,ai,llm,root-cause-analysis
Classifier: Development Status :: 4 - Beta
Classifier: Intended Audience :: Developers
Classifier: Operating System :: OS Independent
Classifier: Programming Language :: Python :: 3
Classifier: Programming Language :: Python :: 3.9
Classifier: Programming Language :: Python :: 3.10
Classifier: Programming Language :: Python :: 3.11
Classifier: Programming Language :: Python :: 3.12
Classifier: Topic :: Software Development :: Build Tools
Classifier: Topic :: Software Development :: Debuggers
Classifier: Topic :: System :: Logging
Classifier: Topic :: Scientific/Engineering :: Artificial Intelligence
Requires-Python: >=3.9
License-File: LICENSE
Requires-Dist: anthropic>=0.34.0
Requires-Dist: google-generativeai>=0.3.0
Requires-Dist: openai>=1.0.0
Requires-Dist: boto3>=1.28.0
Requires-Dist: click>=8.1.0
Requires-Dist: requests>=2.31.0
Requires-Dist: tiktoken>=0.5.0
Requires-Dist: langchain-text-splitters>=0.2.0
Dynamic: license-file
